undumper/__init__.py
undumper/undumper.py
undumper-1.0.0.dist-info/LICENSE
undumper-1.0.0.dist-info/METADATA
undumper-1.0.0.dist-info/WHEEL
undumper-1.0.0.dist-info/RECORD
