Metadata-Version: 2.1
Name: unDumper
Version: 1.0.0
Summary: A fast and memory-efficient LAMMPS dump file reader with great developer experience
License: MIT
Author: Mohid Farooqi
Author-email: mu2farooqi@uwaterloo.ca
Requires-Python: >=3.12,<4.0
Classifier: License :: OSI Approved :: MIT License
Classifier: Programming Language :: Python :: 3
Classifier: Programming Language :: Python :: 3.12
Requires-Dist: pyyaml (>=6.0.1,<7.0.0)
